{
  "slug": "palatal-expanders",
  "title": "上颌扩弓器",
  "subtitle": "纽约法拉盛和大颈地区的腭扩展器治疗",
  "icon": "Maximize",
  "category": "specialized",
  "featured": false,
  "heroVariant": "split-photo-right",
  "image": "https://mmcmvmwcktqdeflcwfks.supabase.co/storage/v1/object/public/dental-media/hu-orthodontics/services/1776497744415-palatal-expanders.jpg",
  "price": "起价 $2,000",
  "durationMinutes": null,
  "shortDescription": "针对上颌狭窄儿童的上颌扩弓治疗，为正常牙齿萌出和均衡咬合创造所需空间。",
  "sections": [
    {
      "type": "intro",
      "title": "什么是腭扩展器？",
      "content": "腭扩展器（上颌扩弓器）是一种专门用于扩宽生长发育期儿童上颌骨的正畸装置。当孩子的上颌过于狭窄时，会导致牙齿拥挤、后牙锁合（crossbite）、恒牙阻生以及呼吸困难等问题。腭扩展器通过温和地扩宽上颌腭中缝，创造真实的骨骼宽度增加。",
      "content2": "该装置利用儿童的自然生长发育优势，在腭中缝尚未完全融合时进行干预。扩弓治疗的最佳年龄为六至十四岁。通过早期干预，可以为恒牙萌出创造充足的空间，避免未来可能需要的拔牙治疗，并为后续正畸治疗奠定良好的基础。",
      "image": "https://images.unsplash.com/photo-1609840114035-3c981b782dfe?w=600&h=450&fit=crop",
      "imagePosition": "right"
    },
    {
      "type": "candidates",
      "title": "哪些孩子需要腭扩展器？",
      "content": "以下情况的儿童可能需要使用腭扩展器进行早期矫治：",
      "items": [
        "上颌骨过于狭窄",
        "后牙锁合（上牙弓比下牙弓窄）",
        "牙齿严重拥挤，空间不足",
        "恒牙萌出受阻",
        "习惯性口呼吸",
        "打鼾或轻度睡眠呼吸问题",
        "面中部发育不足"
      ],
      "image": "https://images.unsplash.com/photo-1598256989800-fe5f95da9787?w=600&h=450&fit=crop"
    },
    {
      "type": "advantages",
      "title": "腭扩展器的优势",
      "items": [
        {
          "icon": "TrendingUp",
          "title": "利用生长发育优势",
          "description": "在腭中缝尚未融合时进行治疗，通过真实的骨骼扩展实现更稳定、更持久的效果。"
        },
        {
          "icon": "Maximize",
          "title": "创造空间避免拔牙",
          "description": "通过扩宽牙弓创造足够的空间，让恒牙自然萌出到正确位置，减少或消除未来拔牙的需要。"
        },
        {
          "icon": "Wind",
          "title": "改善呼吸功能",
          "description": "上颌扩弓可以扩大鼻腔底部，改善鼻呼吸通畅性，帮助解决口呼吸和打鼾问题。"
        },
        {
          "icon": "Timer",
          "title": "缩短后续治疗时间",
          "description": "早期扩弓可以简化未来的正畸治疗，缩短牙套佩戴时间，降低整体治疗复杂度。"
        }
      ]
    },
    {
      "type": "process",
      "title": "腭扩展器治疗流程",
      "steps": [
        {
          "number": 1,
          "title": "全面评估",
          "description": "通过数字X光片、口内扫描和临床检查，评估孩子上颌的宽度和发育状况，确定是否需要扩弓治疗。"
        },
        {
          "number": 2,
          "title": "定制与安装",
          "description": "根据孩子的口腔取模制作专属扩弓器，安装就诊时将装置粘固到位，并教会家长如何操作加力钥匙。"
        },
        {
          "number": 3,
          "title": "每日加力",
          "description": "家长按照处方每天旋转扩弓螺丝一至两次，主动扩展阶段通常持续两到四周。"
        },
        {
          "number": 4,
          "title": "巩固稳定期",
          "description": "达到目标扩展量后，扩弓器继续保留三至六个月作为被动保持器，等待新骨组织填充和稳定。"
        },
        {
          "number": 5,
          "title": "拆除与后续规划",
          "description": "稳定期结束后取下扩弓器，评估效果并制定后续正畸治疗计划。"
        }
      ]
    },
    {
      "type": "whyUs",
      "title": "为什么选择胡林医生？",
      "items": [
        {
          "icon": "Award",
          "title": "ABO三次认证专家",
          "description": "胡林医生是三次获得美国正畸学会认证的正畸专家。"
        },
        {
          "icon": "Globe",
          "title": "中英双语沟通",
          "description": "团队精通普通话和英语。"
        },
        {
          "icon": "Clock",
          "title": "灵活就诊时间",
          "description": "法拉盛和大颈两处诊所，提供周末预约。"
        },
        {
          "icon": "Scan",
          "title": "先进设备",
          "description": "配备先进的数字化正畸设备。"
        }
      ]
    }
  ],
  "faq": [
    {
      "question": "上颌扩弓器的理想年龄是多大？",
      "answer": "上颌扩弓器在六至十四岁的儿童中效果最佳，此时腭中缝仍在发育，可以被温和地扩展。在较年幼的患者中，扩展是通过实际的骨骼生长而非仅仅是牙齿倾斜来实现的，这会产生更稳定和可预测的效果。建议在七岁左右进行早期正畸评估，以确定您的孩子是否适合扩弓治疗。"
    },
    {
      "question": "上颌扩弓器会疼吗？",
      "answer": "您的孩子在每次加力调节扩弓器后可能会感到几分钟的压力或轻微不适，但这种感觉通常很快消退。大多数孩子在第一周内就能适应这个装置。扩展过程是循序渐进的，每天进行微小的调整，因此施加的力量是轻柔且可耐受的。"
    },
    {
      "question": "上颌扩弓器的治疗需要多长时间？",
      "answer": "主动扩展阶段通常持续两到四周，在此期间您将按照指示每天旋转扩弓螺丝一到两次。达到预期的扩展量后，扩弓器将继续保留三到六个月，以使新骨填充扩展的腭中缝并稳定效果。扩弓器的总佩戴时间通常为四到八个月。"
    },
    {
      "question": "我的孩子门牙之间会出现缝隙吗？",
      "answer": "在扩展过程中上门牙之间出现间隙是正常的。这个间隙实际上是上颌正在如预期扩宽的积极信号。扩展完成后，这个间隙通常在几周到几个月内自行关闭，任何残留的间隙都可以在后续的正畸治疗中轻松处理。"
    },
    {
      "question": "扩弓后还需要戴牙套吗？",
      "answer": "大多数情况下，扩弓治疗是全面正畸治疗计划的第一阶段。扩弓器创造了足够的空间后，孩子可能需要在恒牙全部萌出后进行第二阶段的牙套治疗，以精细调整牙齿排列和咬合关系。早期扩弓通常可以显著简化和缩短后续的牙套治疗。"
    }
  ],
  "cta": {
    "title": "关注孩子的口腔发育",
    "subtitle": "预约早期正畸评估，把握最佳治疗时机",
    "primaryCta": {
      "link": "/contact",
      "text": "预约免费咨询"
    },
    "secondaryCta": {
      "link": "tel:+17183530880",
      "text": "(718) 353-0880"
    }
  }
}
