{
  "home": {
    "title": "纽约牙齿矫正｜法拉盛与大颈ABO认证正畸专家｜胡林正畸中心",
    "description": "胡林医生是三次获得ABO认证的正畸专家。法拉盛与大颈两处门诊提供牙齿矫正、隐适美、牙套、儿童与成人正畸服务，中英双语咨询。"
  },
  "pages": {
    "blog": {
      "title": "牙齿矫正与正畸知识中心 — 胡林正畸中心",
      "description": "了解牙齿矫正、隐适美、牙套护理等正畸知识。胡林医生团队提供面向纽约华人的专业科普内容。"
    },
    "team": {
      "title": "我们的团队 — 胡林正畸中心",
      "description": "认识胡林医生及其专业正畸团队。ABO认证正畸专家，中英双语服务。"
    },
    "about": {
      "title": "关于胡林医生｜ABO三次认证牙齿矫正/正畸专家",
      "description": "了解胡林医生背景：DMD、DDS、MS、PhD四重学位，三次获得ABO认证，拥有丰富牙齿矫正与正畸临床经验。"
    },
    "cases": {
      "title": "牙齿矫正案例展示｜正畸前后对比｜胡林正畸中心",
      "description": "查看牙齿矫正前后对比案例，了解不同正畸方案在拥挤、深覆合、反颌等问题上的改善路径。"
    },
    "contact": {
      "title": "预约牙齿矫正咨询｜联系我们｜胡林正畸中心",
      "description": "预约牙齿矫正/正畸初诊。法拉盛诊所 (718) 353-0880，大颈诊所 (516) 809-8686，中英双语服务。"
    },
    "reviews": {
      "title": "患者评价 — 胡林正畸中心",
      "description": "阅读患者对胡林正畸中心的真实评价。了解为什么数千名患者选择胡林医生进行牙齿矫正。"
    },
    "services": {
      "title": "牙齿矫正服务｜隐适美、牙套、儿童与成人正畸｜胡林正畸中心",
      "description": "覆盖传统牙套、陶瓷牙套、隐适美、儿童早期矫治与成人正畸。以牙齿矫正为主线，匹配不同咬合复杂度。"
    },
    "insurance": {
      "title": "保险与付款方案 — 胡林正畸中心",
      "description": "了解我们接受的保险计划和灵活的付款方案。提供免息分期付款选项。"
    },
    "new-patient": {
      "title": "牙齿矫正初诊流程｜新患者须知｜胡林正畸中心",
      "description": "首次牙齿矫正/正畸就诊指南：评估流程、检查项目、方案沟通与疗程预估，帮助新患者快速了解初诊安排。"
    }
  },
  "title": "纽约牙齿矫正｜法拉盛与大颈ABO认证正畸专家｜胡林正畸中心",
  "ogImage": "",
  "description": "胡林医生是三次获得ABO认证的正畸专家，在法拉盛和大颈设有两家诊所。专注牙齿矫正、隐适美、儿童与成人正畸，中英双语服务。"
}